[
    {
        "ID": "36",
        "name_prefix": "Fuzz",
        "name_suffix": "fern",
        "specsuffix_hidden": false,
        "gender": "male",
        "gender_align": "male",
        "birth_cooldown": 0,
        "status": "warrior",
        "backstory": "clan_founder",
        "moons": 29,
        "trait": "charismatic",
        "facets": "10,13,13,5",
        "parent1": null,
        "parent2": null,
        "adoptive_parents": [],
        "mentor": null,
        "former_mentor": [
            "46"
        ],
        "patrol_with_mentor": 0,
        "mate": [],
        "previous_mates": [],
        "dead": false,
        "paralyzed": false,
        "no_kits": false,
        "exiled": false,
        "pelt_name": "Classic",
        "pelt_color": "LILAC",
        "pelt_length": "medium",
        "sprite_kitten": 2,
        "sprite_adolescent": 4,
        "sprite_adult": 7,
        "sprite_senior": 14,
        "sprite_para_adult": 15,
        "eye_colour": "SILVER",
        "eye_colour2": null,
        "reverse": true,
        "white_patches": "PETAL",
        "vitiligo": null,
        "points": null,
        "white_patches_tint": "offwhite",
        "pattern": null,
        "tortie_base": null,
        "tortie_color": null,
        "tortie_pattern": null,
        "skin": "BLACK",
        "tint": "yellow",
        "skill_dict": {
            "primary": "INSIGHTFUL,12,False",
            "secondary": null,
            "hidden": null
        },
        "scars": [],
        "accessory": null,
        "experience": 60,
        "dead_moons": 0,
        "current_apprentice": [],
        "former_apprentices": [
            "41"
        ],
        "df": false,
        "outside": false,
        "otherclan1": false,
        "clan": "Rat",
        "faded_offspring": [],
        "opacity": 100,
        "prevent_fading": false,
        "favourite": false
    },
    {
        "ID": "37",
        "name_prefix": "Moth",
        "name_suffix": "whisper",
        "specsuffix_hidden": false,
        "gender": "female",
        "gender_align": "female",
        "birth_cooldown": 0,
        "status": "warrior",
        "backstory": "clan_founder",
        "moons": 115,
        "trait": "faithful",
        "facets": "15,9,6,9",
        "parent1": null,
        "parent2": null,
        "adoptive_parents": [],
        "mentor": null,
        "former_mentor": [],
        "patrol_with_mentor": 0,
        "mate": [],
        "previous_mates": [],
        "dead": true,
        "paralyzed": false,
        "no_kits": false,
        "exiled": false,
        "pelt_name": "TwoColour",
        "pelt_color": "GREY",
        "pelt_length": "short",
        "sprite_kitten": 0,
        "sprite_adolescent": 3,
        "sprite_adult": 6,
        "sprite_senior": 14,
        "sprite_para_adult": 15,
        "eye_colour": "GREY",
        "eye_colour2": null,
        "reverse": true,
        "white_patches": "BUZZARDFANG",
        "vitiligo": null,
        "points": null,
        "white_patches_tint": "offwhite",
        "pattern": null,
        "tortie_base": null,
        "tortie_color": null,
        "tortie_pattern": null,
        "skin": "DARK",
        "tint": "black",
        "skill_dict": {
            "primary": "INSIGHTFUL,16,False",
            "secondary": "STORY,4,False",
            "hidden": null
        },
        "scars": [],
        "accessory": null,
        "experience": 271,
        "dead_moons": 5,
        "current_apprentice": [],
        "former_apprentices": [],
        "df": false,
        "outside": false,
        "otherclan1": false,
        "clan": "Rat",
        "faded_offspring": [],
        "opacity": 99,
        "prevent_fading": false,
        "favourite": false
    },
    {
        "ID": "38",
        "name_prefix": "Brown",
        "name_suffix": "stream",
        "specsuffix_hidden": false,
        "gender": "female",
        "gender_align": "female",
        "birth_cooldown": 0,
        "status": "warrior",
        "backstory": "clan_founder",
        "moons": 52,
        "trait": "childish",
        "facets": "5,11,6,3",
        "parent1": null,
        "parent2": null,
        "adoptive_parents": [],
        "mentor": null,
        "former_mentor": [],
        "patrol_with_mentor": 0,
        "mate": [],
        "previous_mates": [],
        "dead": false,
        "paralyzed": false,
        "no_kits": false,
        "exiled": false,
        "pelt_name": "Speckled",
        "pelt_color": "CHOCOLATE",
        "pelt_length": "medium",
        "sprite_kitten": 2,
        "sprite_adolescent": 3,
        "sprite_adult": 7,
        "sprite_senior": 13,
        "sprite_para_adult": 15,
        "eye_colour": "GREEN",
        "eye_colour2": null,
        "reverse": false,
        "white_patches": null,
        "vitiligo": null,
        "points": null,
        "white_patches_tint": "none",
        "pattern": null,
        "tortie_base": null,
        "tortie_color": null,
        "tortie_pattern": null,
        "skin": "SALMON",
        "tint": "purple",
        "skill_dict": {
            "primary": "INSIGHTFUL,17,False",
            "secondary": "FIGHTER,10,False",
            "hidden": null
        },
        "scars": [],
        "accessory": null,
        "experience": 227,
        "dead_moons": 0,
        "current_apprentice": [],
        "former_apprentices": [
            "43"
        ],
        "df": false,
        "outside": false,
        "otherclan1": false,
        "clan": "Rat",
        "faded_offspring": [],
        "opacity": 100,
        "prevent_fading": false,
        "favourite": false
    },
    {
        "ID": "39",
        "name_prefix": "Marsh",
        "name_suffix": "lilac",
        "specsuffix_hidden": false,
        "gender": "male",
        "gender_align": "trans female",
        "birth_cooldown": 0,
        "status": "leader",
        "backstory": "clan_founder",
        "moons": 117,
        "trait": "troublesome",
        "facets": "6,3,3,2",
        "parent1": null,
        "parent2": null,
        "adoptive_parents": [],
        "mentor": null,
        "former_mentor": [],
        "patrol_with_mentor": 0,
        "mate": [],
        "previous_mates": [],
        "dead": false,
        "paralyzed": false,
        "no_kits": false,
        "exiled": false,
        "pelt_name": "SingleColour",
        "pelt_color": "LILAC",
        "pelt_length": "medium",
        "sprite_kitten": 0,
        "sprite_adolescent": 4,
        "sprite_adult": 7,
        "sprite_senior": 14,
        "sprite_para_adult": 15,
        "eye_colour": "GREY",
        "eye_colour2": null,
        "reverse": true,
        "white_patches": "HONEY",
        "vitiligo": null,
        "points": null,
        "white_patches_tint": "darkcream",
        "pattern": null,
        "tortie_base": null,
        "tortie_color": null,
        "tortie_pattern": null,
        "skin": "LIGHTMARBLED",
        "tint": "purple",
        "skill_dict": {
            "primary": "STAR,9,False",
            "secondary": null,
            "hidden": null
        },
        "scars": [],
        "accessory": "MOTH WINGS",
        "experience": 306,
        "dead_moons": 0,
        "current_apprentice": [],
        "former_apprentices": [
            "44"
        ],
        "df": false,
        "outside": false,
        "otherclan1": false,
        "clan": "Rat",
        "faded_offspring": [],
        "opacity": 100,
        "prevent_fading": false,
        "favourite": false
    },
    {
        "ID": "41",
        "name_prefix": "Sprout",
        "name_suffix": "pelt",
        "specsuffix_hidden": false,
        "gender": "male",
        "gender_align": "male",
        "birth_cooldown": 0,
        "status": "warrior",
        "backstory": "clan_founder",
        "moons": 19,
        "trait": "shameless",
        "facets": "5,14,8,9",
        "parent1": null,
        "parent2": null,
        "adoptive_parents": [],
        "mentor": null,
        "former_mentor": [
            "36"
        ],
        "patrol_with_mentor": 0,
        "mate": [],
        "previous_mates": [],
        "dead": false,
        "paralyzed": false,
        "no_kits": false,
        "exiled": false,
        "pelt_name": "Smoke",
        "pelt_color": "BLACK",
        "pelt_length": "short",
        "sprite_kitten": 2,
        "sprite_adolescent": 4,
        "sprite_adult": 7,
        "sprite_senior": 12,
        "sprite_para_adult": 15,
        "eye_colour": "PALEGREEN",
        "eye_colour2": null,
        "reverse": true,
        "white_patches": null,
        "vitiligo": null,
        "points": null,
        "white_patches_tint": "none",
        "pattern": null,
        "tortie_base": null,
        "tortie_color": null,
        "tortie_pattern": null,
        "skin": "DARK",
        "tint": "blue",
        "skill_dict": {
            "primary": "FIGHTER,7,False",
            "secondary": "SENSE,10,False",
            "hidden": null
        },
        "scars": [],
        "accessory": null,
        "experience": 57,
        "dead_moons": 0,
        "current_apprentice": [],
        "former_apprentices": [],
        "df": false,
        "outside": false,
        "otherclan1": false,
        "clan": "Rat",
        "faded_offspring": [],
        "opacity": 100,
        "prevent_fading": false,
        "favourite": false
    },
    {
        "ID": "42",
        "name_prefix": "Chanterelle",
        "name_suffix": "echo",
        "specsuffix_hidden": false,
        "gender": "female",
        "gender_align": "female",
        "birth_cooldown": 0,
        "status": "medicine cat",
        "backstory": "clan_founder",
        "moons": 36,
        "trait": "strict",
        "facets": "14,6,10,16",
        "parent1": null,
        "parent2": null,
        "adoptive_parents": [],
        "mentor": null,
        "former_mentor": [],
        "patrol_with_mentor": 0,
        "mate": [],
        "previous_mates": [],
        "dead": false,
        "paralyzed": false,
        "no_kits": false,
        "exiled": false,
        "pelt_name": "SingleColour",
        "pelt_color": "CHOCOLATE",
        "pelt_length": "medium",
        "sprite_kitten": 0,
        "sprite_adolescent": 4,
        "sprite_adult": 8,
        "sprite_senior": 14,
        "sprite_para_adult": 15,
        "eye_colour": "COBALT",
        "eye_colour2": null,
        "reverse": false,
        "white_patches": "MISS",
        "vitiligo": null,
        "points": null,
        "white_patches_tint": "offwhite",
        "pattern": null,
        "tortie_base": null,
        "tortie_color": null,
        "tortie_pattern": null,
        "skin": "GREY",
        "tint": "yellow",
        "skill_dict": {
            "primary": "KIT,21,False",
            "secondary": "CAMP,15,False",
            "hidden": null
        },
        "scars": [],
        "accessory": null,
        "experience": 52,
        "dead_moons": 0,
        "current_apprentice": [],
        "former_apprentices": [],
        "df": false,
        "outside": false,
        "otherclan1": false,
        "clan": "Rat",
        "faded_offspring": [],
        "opacity": 100,
        "prevent_fading": false,
        "favourite": false
    },
    {
        "ID": "43",
        "name_prefix": "Blue",
        "name_suffix": "swarm",
        "specsuffix_hidden": false,
        "gender": "female",
        "gender_align": "female",
        "birth_cooldown": 0,
        "status": "warrior",
        "backstory": "clan_founder",
        "moons": 27,
        "trait": "ambitious",
        "facets": "11,12,14,8",
        "parent1": null,
        "parent2": null,
        "adoptive_parents": [],
        "mentor": null,
        "former_mentor": [
            "38"
        ],
        "patrol_with_mentor": 0,
        "mate": [],
        "previous_mates": [],
        "dead": false,
        "paralyzed": false,
        "no_kits": false,
        "exiled": false,
        "pelt_name": "Singlestripe",
        "pelt_color": "GOLDEN-BROWN",
        "pelt_length": "short",
        "sprite_kitten": 1,
        "sprite_adolescent": 5,
        "sprite_adult": 8,
        "sprite_senior": 13,
        "sprite_para_adult": 15,
        "eye_colour": "PALEBLUE",
        "eye_colour2": null,
        "reverse": false,
        "white_patches": null,
        "vitiligo": null,
        "points": null,
        "white_patches_tint": "none",
        "pattern": null,
        "tortie_base": null,
        "tortie_color": null,
        "tortie_pattern": null,
        "skin": "LIGHTBROWN",
        "tint": "black",
        "skill_dict": {
            "primary": "RUNNER,13,False",
            "secondary": "FIGHTER,4,False",
            "hidden": null
        },
        "scars": [],
        "accessory": null,
        "experience": 51,
        "dead_moons": 0,
        "current_apprentice": [],
        "former_apprentices": [],
        "df": false,
        "outside": false,
        "otherclan1": false,
        "clan": "Rat",
        "faded_offspring": [],
        "opacity": 100,
        "prevent_fading": false,
        "favourite": false
    },
    {
        "ID": "44",
        "name_prefix": "Borage",
        "name_suffix": "poppy",
        "specsuffix_hidden": false,
        "gender": "male",
        "gender_align": "male",
        "birth_cooldown": 0,
        "status": "warrior",
        "backstory": "clan_founder",
        "moons": 25,
        "trait": "adventurous",
        "facets": "7,12,5,15",
        "parent1": null,
        "parent2": null,
        "adoptive_parents": [],
        "mentor": null,
        "former_mentor": [
            "39"
        ],
        "patrol_with_mentor": 0,
        "mate": [],
        "previous_mates": [],
        "dead": false,
        "paralyzed": false,
        "no_kits": false,
        "exiled": false,
        "pelt_name": "Agouti",
        "pelt_color": "GOLDEN-BROWN",
        "pelt_length": "short",
        "sprite_kitten": 2,
        "sprite_adolescent": 5,
        "sprite_adult": 6,
        "sprite_senior": 13,
        "sprite_para_adult": 15,
        "eye_colour": "BLUE",
        "eye_colour2": null,
        "reverse": false,
        "white_patches": null,
        "vitiligo": null,
        "points": null,
        "white_patches_tint": "none",
        "pattern": null,
        "tortie_base": null,
        "tortie_color": null,
        "tortie_pattern": null,
        "skin": "RED",
        "tint": "yellow",
        "skill_dict": {
            "primary": "KIT,14,False",
            "secondary": "CLIMBER,7,False",
            "hidden": null
        },
        "scars": [],
        "accessory": null,
        "experience": 51,
        "dead_moons": 0,
        "current_apprentice": [],
        "former_apprentices": [],
        "df": false,
        "outside": false,
        "otherclan1": false,
        "clan": "Rat",
        "faded_offspring": [],
        "opacity": 100,
        "prevent_fading": false,
        "favourite": false
    },
    {
        "ID": "46",
        "name_prefix": "Skip",
        "name_suffix": "twist",
        "specsuffix_hidden": false,
        "gender": "female",
        "gender_align": "female",
        "birth_cooldown": 0,
        "status": "deputy",
        "backstory": "clan_founder",
        "moons": 135,
        "trait": "ambitious",
        "facets": "15,10,14,7",
        "parent1": null,
        "parent2": null,
        "adoptive_parents": [],
        "mentor": null,
        "former_mentor": [],
        "patrol_with_mentor": 0,
        "mate": [],
        "previous_mates": [],
        "dead": false,
        "paralyzed": false,
        "no_kits": false,
        "exiled": false,
        "pelt_name": "TwoColour",
        "pelt_color": "BROWN",
        "pelt_length": "medium",
        "sprite_kitten": 2,
        "sprite_adolescent": 4,
        "sprite_adult": 8,
        "sprite_senior": 13,
        "sprite_para_adult": 15,
        "eye_colour": "PALEYELLOW",
        "eye_colour2": null,
        "reverse": false,
        "white_patches": "BLACKSTAR",
        "vitiligo": null,
        "points": null,
        "white_patches_tint": "offwhite",
        "pattern": null,
        "tortie_base": null,
        "tortie_color": null,
        "tortie_pattern": null,
        "skin": "BLUE",
        "tint": "yellow",
        "skill_dict": {
            "primary": "SENSE,20,False",
            "secondary": "CAMP,1,False",
            "hidden": null
        },
        "scars": [],
        "accessory": null,
        "experience": 136,
        "dead_moons": 0,
        "current_apprentice": [],
        "former_apprentices": [
            "36",
            "47"
        ],
        "df": false,
        "outside": false,
        "otherclan1": false,
        "clan": "Rat",
        "faded_offspring": [],
        "opacity": 100,
        "prevent_fading": false,
        "favourite": false
    },
    {
        "ID": "47",
        "name_prefix": "Swamp",
        "name_suffix": "stripe",
        "specsuffix_hidden": false,
        "gender": "male",
        "gender_align": "male",
        "birth_cooldown": 0,
        "status": "warrior",
        "backstory": "clan_founder",
        "moons": 21,
        "trait": "playful",
        "facets": "8,9,2,10",
        "parent1": null,
        "parent2": null,
        "adoptive_parents": [],
        "mentor": null,
        "former_mentor": [
            "46"
        ],
        "patrol_with_mentor": 0,
        "mate": [],
        "previous_mates": [],
        "dead": false,
        "paralyzed": false,
        "no_kits": false,
        "exiled": false,
        "pelt_name": "Speckled",
        "pelt_color": "GINGER",
        "pelt_length": "medium",
        "sprite_kitten": 0,
        "sprite_adolescent": 4,
        "sprite_adult": 6,
        "sprite_senior": 14,
        "sprite_para_adult": 15,
        "eye_colour": "PALEBLUE",
        "eye_colour2": null,
        "reverse": true,
        "white_patches": null,
        "vitiligo": null,
        "points": null,
        "white_patches_tint": "none",
        "pattern": null,
        "tortie_base": null,
        "tortie_color": null,
        "tortie_pattern": null,
        "skin": "PINK",
        "tint": "pink",
        "skill_dict": {
            "primary": "HUNTER,10,False",
            "secondary": null,
            "hidden": null
        },
        "scars": [],
        "accessory": null,
        "experience": 60,
        "dead_moons": 0,
        "current_apprentice": [],
        "former_apprentices": [],
        "df": false,
        "outside": false,
        "otherclan1": false,
        "clan": "Rat",
        "faded_offspring": [],
        "opacity": 100,
        "prevent_fading": false,
        "favourite": false
    },
    {
        "ID": "48",
        "name_prefix": "Weed",
        "name_suffix": "chase",
        "specsuffix_hidden": false,
        "gender": "male",
        "gender_align": "male",
        "birth_cooldown": 0,
        "status": "deputy",
        "backstory": "clan_founder",
        "moons": 75,
        "trait": "lonesome",
        "facets": "3,1,5,10",
        "parent1": null,
        "parent2": null,
        "adoptive_parents": [],
        "mentor": null,
        "former_mentor": [],
        "patrol_with_mentor": 0,
        "mate": [],
        "previous_mates": [],
        "dead": true,
        "paralyzed": false,
        "no_kits": false,
        "exiled": false,
        "pelt_name": "Mackerel",
        "pelt_color": "GOLDEN-BROWN",
        "pelt_length": "long",
        "sprite_kitten": 1,
        "sprite_adolescent": 4,
        "sprite_adult": 11,
        "sprite_senior": 13,
        "sprite_para_adult": 15,
        "eye_colour": "PALEGREEN",
        "eye_colour2": null,
        "reverse": false,
        "white_patches": null,
        "vitiligo": null,
        "points": null,
        "white_patches_tint": "none",
        "pattern": null,
        "tortie_base": null,
        "tortie_color": null,
        "tortie_pattern": null,
        "skin": "LIGHTBROWN",
        "tint": "pink",
        "skill_dict": {
            "primary": "SENSE,14,False",
            "secondary": null,
            "hidden": null
        },
        "scars": [],
        "accessory": null,
        "experience": 232,
        "dead_moons": 137,
        "current_apprentice": [],
        "former_apprentices": [],
        "df": false,
        "outside": false,
        "otherclan1": false,
        "clan": "Jump",
        "faded_offspring": [],
        "opacity": 100,
        "prevent_fading": false,
        "favourite": false
    },
    {
        "ID": "49",
        "name_prefix": "Rush",
        "name_suffix": "wood",
        "specsuffix_hidden": false,
        "gender": "female",
        "gender_align": "female",
        "birth_cooldown": 0,
        "status": "medicine cat",
        "backstory": "clanborn",
        "moons": 25,
        "trait": "compassionate",
        "facets": "9,9,6,2",
        "parent1": null,
        "parent2": null,
        "adoptive_parents": [],
        "mentor": null,
        "former_mentor": [],
        "patrol_with_mentor": 0,
        "mate": [],
        "previous_mates": [],
        "dead": false,
        "paralyzed": false,
        "no_kits": false,
        "exiled": false,
        "pelt_name": "Singlestripe",
        "pelt_color": "DARKGREY",
        "pelt_length": "long",
        "sprite_kitten": 0,
        "sprite_adolescent": 3,
        "sprite_adult": 11,
        "sprite_senior": 14,
        "sprite_para_adult": 15,
        "eye_colour": "PALEGREEN",
        "eye_colour2": null,
        "reverse": false,
        "white_patches": null,
        "vitiligo": null,
        "points": null,
        "white_patches_tint": "none",
        "pattern": null,
        "tortie_base": null,
        "tortie_color": null,
        "tortie_pattern": null,
        "skin": "MARBLED",
        "tint": "pink",
        "skill_dict": {
            "primary": "TEACHER,7,False",
            "secondary": "PROPHET,11,False",
            "hidden": null
        },
        "scars": [],
        "accessory": null,
        "experience": 30,
        "dead_moons": 0,
        "current_apprentice": [],
        "former_apprentices": [],
        "df": false,
        "outside": true,
        "otherclan1": true,
        "clan": "Speckle",
        "faded_offspring": [],
        "opacity": 100,
        "prevent_fading": false,
        "favourite": false
    },
    {
        "ID": "50",
        "name_prefix": "Sleet",
        "name_suffix": "flash",
        "specsuffix_hidden": false,
        "gender": "female",
        "gender_align": "female",
        "birth_cooldown": 0,
        "status": "warrior",
        "backstory": "clanborn",
        "moons": 24,
        "trait": "adventurous",
        "facets": "1,13,4,9",
        "parent1": null,
        "parent2": null,
        "adoptive_parents": [],
        "mentor": null,
        "former_mentor": [
            "60",
            "59"
        ],
        "patrol_with_mentor": 0,
        "mate": [],
        "previous_mates": [],
        "dead": false,
        "paralyzed": false,
        "no_kits": false,
        "exiled": false,
        "pelt_name": "Marbled",
        "pelt_color": "WHITE",
        "pelt_length": "long",
        "sprite_kitten": 2,
        "sprite_adolescent": 3,
        "sprite_adult": 10,
        "sprite_senior": 14,
        "sprite_para_adult": 15,
        "eye_colour": "DARKBLUE",
        "eye_colour2": null,
        "reverse": false,
        "white_patches": "SCOURGE",
        "vitiligo": null,
        "points": null,
        "white_patches_tint": "none",
        "pattern": null,
        "tortie_base": null,
        "tortie_color": null,
        "tortie_pattern": null,
        "skin": "PEACH",
        "tint": "yellow",
        "skill_dict": {
            "primary": "SENSE,3,False",
            "secondary": "SWIMMER,9,False",
            "hidden": null
        },
        "scars": [],
        "accessory": null,
        "experience": 46,
        "dead_moons": 0,
        "current_apprentice": [],
        "former_apprentices": [],
        "df": false,
        "outside": true,
        "otherclan1": true,
        "clan": "Speckle",
        "faded_offspring": [],
        "opacity": 100,
        "prevent_fading": false,
        "favourite": false
    },
    {
        "ID": "51",
        "name_prefix": "Nectar",
        "name_suffix": "fire",
        "specsuffix_hidden": false,
        "gender": "male",
        "gender_align": "male",
        "birth_cooldown": 0,
        "status": "warrior",
        "backstory": "clanborn",
        "moons": 24,
        "trait": "nervous",
        "facets": "16,1,5,0",
        "parent1": null,
        "parent2": null,
        "adoptive_parents": [],
        "mentor": null,
        "former_mentor": [
            "59"
        ],
        "patrol_with_mentor": 0,
        "mate": [],
        "previous_mates": [],
        "dead": false,
        "paralyzed": false,
        "no_kits": false,
        "exiled": false,
        "pelt_name": "Smoke",
        "pelt_color": "SILVER",
        "pelt_length": "short",
        "sprite_kitten": 2,
        "sprite_adolescent": 4,
        "sprite_adult": 6,
        "sprite_senior": 12,
        "sprite_para_adult": 15,
        "eye_colour": "SAGE",
        "eye_colour2": null,
        "reverse": true,
        "white_patches": null,
        "vitiligo": null,
        "points": null,
        "white_patches_tint": "none",
        "pattern": null,
        "tortie_base": null,
        "tortie_color": null,
        "tortie_pattern": null,
        "skin": "LIGHTBLUE",
        "tint": "none",
        "skill_dict": {
            "primary": "CLEVER,9,False",
            "secondary": null,
            "hidden": null
        },
        "scars": [],
        "accessory": null,
        "experience": 53,
        "dead_moons": 0,
        "current_apprentice": [],
        "former_apprentices": [],
        "df": false,
        "outside": true,
        "otherclan1": true,
        "clan": "Speckle",
        "faded_offspring": [],
        "opacity": 100,
        "prevent_fading": false,
        "favourite": false
    },
    {
        "ID": "52",
        "name_prefix": "Hollow",
        "name_suffix": "lilac",
        "specsuffix_hidden": false,
        "gender": "male",
        "gender_align": "male",
        "birth_cooldown": 0,
        "status": "warrior",
        "backstory": "clanborn",
        "moons": 23,
        "trait": "calm",
        "facets": "9,8,5,11",
        "parent1": null,
        "parent2": null,
        "adoptive_parents": [],
        "mentor": null,
        "former_mentor": [
            "55"
        ],
        "patrol_with_mentor": 0,
        "mate": [],
        "previous_mates": [],
        "dead": false,
        "paralyzed": false,
        "no_kits": false,
        "exiled": false,
        "pelt_name": "Bengal",
        "pelt_color": "DARKGREY",
        "pelt_length": "long",
        "sprite_kitten": 2,
        "sprite_adolescent": 4,
        "sprite_adult": 9,
        "sprite_senior": 13,
        "sprite_para_adult": 15,
        "eye_colour": "PALEBLUE",
        "eye_colour2": null,
        "reverse": false,
        "white_patches": "PIEBALD",
        "vitiligo": null,
        "points": null,
        "white_patches_tint": "offwhite",
        "pattern": null,
        "tortie_base": null,
        "tortie_color": null,
        "tortie_pattern": null,
        "skin": "PINK",
        "tint": "pink",
        "skill_dict": {
            "primary": "FIGHTER,3,False",
            "secondary": null,
            "hidden": null
        },
        "scars": [],
        "accessory": null,
        "experience": 51,
        "dead_moons": 0,
        "current_apprentice": [],
        "former_apprentices": [],
        "df": false,
        "outside": true,
        "otherclan1": true,
        "clan": "Speckle",
        "faded_offspring": [],
        "opacity": 100,
        "prevent_fading": false,
        "favourite": false
    },
    {
        "ID": "53",
        "name_prefix": "Kite",
        "name_suffix": "tail",
        "specsuffix_hidden": false,
        "gender": "female",
        "gender_align": "female",
        "birth_cooldown": 0,
        "status": "deputy",
        "backstory": "clanborn",
        "moons": 24,
        "trait": "fierce",
        "facets": "1,5,9,6",
        "parent1": null,
        "parent2": null,
        "adoptive_parents": [],
        "mentor": null,
        "former_mentor": [
            "55"
        ],
        "patrol_with_mentor": 0,
        "mate": [],
        "previous_mates": [],
        "dead": false,
        "paralyzed": false,
        "no_kits": false,
        "exiled": false,
        "pelt_name": "Tortie",
        "pelt_color": "CHOCOLATE",
        "pelt_length": "short",
        "sprite_kitten": 0,
        "sprite_adolescent": 4,
        "sprite_adult": 7,
        "sprite_senior": 14,
        "sprite_para_adult": 15,
        "eye_colour": "CYAN",
        "eye_colour2": null,
        "reverse": true,
        "white_patches": null,
        "vitiligo": null,
        "points": null,
        "white_patches_tint": "none",
        "pattern": "ROBIN",
        "tortie_base": "single",
        "tortie_color": "GHOST",
        "tortie_pattern": "ticked",
        "skin": "DARK",
        "tint": "gray",
        "skill_dict": {
            "primary": "CLEVER,9,False",
            "secondary": null,
            "hidden": null
        },
        "scars": [],
        "accessory": null,
        "experience": 51,
        "dead_moons": 0,
        "current_apprentice": [],
        "former_apprentices": [],
        "df": false,
        "outside": true,
        "otherclan1": true,
        "clan": "Speckle",
        "faded_offspring": [],
        "opacity": 100,
        "prevent_fading": false,
        "favourite": false
    },
    {
        "ID": "54",
        "name_prefix": "Jump",
        "name_suffix": "nut",
        "specsuffix_hidden": false,
        "gender": "male",
        "gender_align": "male",
        "birth_cooldown": 0,
        "status": "elder",
        "backstory": "clanborn",
        "moons": 144,
        "trait": "loyal",
        "facets": "10,16,12,6",
        "parent1": null,
        "parent2": null,
        "adoptive_parents": [],
        "mentor": null,
        "former_mentor": [],
        "patrol_with_mentor": 0,
        "mate": [],
        "previous_mates": [],
        "dead": false,
        "paralyzed": false,
        "no_kits": false,
        "exiled": false,
        "pelt_name": "Marbled",
        "pelt_color": "PALEGREY",
        "pelt_length": "short",
        "sprite_kitten": 0,
        "sprite_adolescent": 3,
        "sprite_adult": 6,
        "sprite_senior": 12,
        "sprite_para_adult": 15,
        "eye_colour": "CYAN",
        "eye_colour2": null,
        "reverse": false,
        "white_patches": "TUXEDO",
        "vitiligo": null,
        "points": null,
        "white_patches_tint": "none",
        "pattern": null,
        "tortie_base": null,
        "tortie_color": null,
        "tortie_pattern": null,
        "skin": "LIGHTBROWN",
        "tint": "pink",
        "skill_dict": {
            "primary": "CLEVER,25,False",
            "secondary": "TEACHER,12,False",
            "hidden": null
        },
        "scars": [],
        "accessory": null,
        "experience": 185,
        "dead_moons": 0,
        "current_apprentice": [],
        "former_apprentices": [],
        "df": false,
        "outside": true,
        "otherclan1": true,
        "clan": "Speckle",
        "faded_offspring": [],
        "opacity": 100,
        "prevent_fading": false,
        "favourite": false
    },
    {
        "ID": "55",
        "name_prefix": "Seed",
        "name_suffix": "shade",
        "specsuffix_hidden": false,
        "gender": "female",
        "gender_align": "female",
        "birth_cooldown": 0,
        "status": "deputy",
        "backstory": "clanborn",
        "moons": 99,
        "trait": "careful",
        "facets": "8,4,5,13",
        "parent1": null,
        "parent2": null,
        "adoptive_parents": [],
        "mentor": null,
        "former_mentor": [],
        "patrol_with_mentor": 0,
        "mate": [],
        "previous_mates": [],
        "dead": true,
        "paralyzed": false,
        "no_kits": false,
        "exiled": false,
        "pelt_name": "Tortie",
        "pelt_color": "GHOST",
        "pelt_length": "short",
        "sprite_kitten": 0,
        "sprite_adolescent": 5,
        "sprite_adult": 7,
        "sprite_senior": 14,
        "sprite_para_adult": 15,
        "eye_colour": "EMERALD",
        "eye_colour2": null,
        "reverse": false,
        "white_patches": "SCOURGE",
        "vitiligo": null,
        "points": null,
        "white_patches_tint": "offwhite",
        "pattern": "FOUR",
        "tortie_base": "mackerel",
        "tortie_color": "DARKGINGER",
        "tortie_pattern": "mackerel",
        "skin": "DARK",
        "tint": "black",
        "skill_dict": {
            "primary": "SWIMMER,22,False",
            "secondary": "FIGHTER,13,False",
            "hidden": null
        },
        "scars": [],
        "accessory": null,
        "experience": 126,
        "dead_moons": 3,
        "current_apprentice": [],
        "former_apprentices": [
            "52",
            "53"
        ],
        "df": false,
        "outside": false,
        "otherclan1": true,
        "clan": "Speckle",
        "faded_offspring": [],
        "opacity": 99,
        "prevent_fading": false,
        "favourite": false
    },
    {
        "ID": "56",
        "name_prefix": "Cone",
        "name_suffix": "patch",
        "specsuffix_hidden": false,
        "gender": "female",
        "gender_align": "female",
        "birth_cooldown": 0,
        "status": "medicine cat",
        "backstory": "clanborn",
        "moons": 25,
        "trait": "vengeful",
        "facets": "6,7,13,0",
        "parent1": null,
        "parent2": null,
        "adoptive_parents": [],
        "mentor": null,
        "former_mentor": [],
        "patrol_with_mentor": 0,
        "mate": [],
        "previous_mates": [],
        "dead": false,
        "paralyzed": false,
        "no_kits": false,
        "exiled": false,
        "pelt_name": "TwoColour",
        "pelt_color": "GREY",
        "pelt_length": "long",
        "sprite_kitten": 0,
        "sprite_adolescent": 5,
        "sprite_adult": 9,
        "sprite_senior": 12,
        "sprite_para_adult": 15,
        "eye_colour": "BLUE",
        "eye_colour2": null,
        "reverse": true,
        "white_patches": "PETAL",
        "vitiligo": null,
        "points": null,
        "white_patches_tint": "none",
        "pattern": null,
        "tortie_base": null,
        "tortie_color": null,
        "tortie_pattern": null,
        "skin": "DARKSALMON",
        "tint": "red",
        "skill_dict": {
            "primary": "SPEAKER,7,False",
            "secondary": "SENSE,1,False",
            "hidden": null
        },
        "scars": [],
        "accessory": null,
        "experience": 36,
        "dead_moons": 0,
        "current_apprentice": [],
        "former_apprentices": [],
        "df": false,
        "outside": true,
        "otherclan1": true,
        "clan": "Speckle",
        "faded_offspring": [],
        "opacity": 100,
        "prevent_fading": false,
        "favourite": false
    },
    {
        "ID": "57",
        "name_prefix": "Prance",
        "name_suffix": "dapple",
        "specsuffix_hidden": false,
        "gender": "male",
        "gender_align": "male",
        "birth_cooldown": 0,
        "status": "elder",
        "backstory": "clanborn",
        "moons": 129,
        "trait": "charismatic",
        "facets": "11,9,9,2",
        "parent1": null,
        "parent2": null,
        "adoptive_parents": [],
        "mentor": null,
        "former_mentor": [],
        "patrol_with_mentor": 0,
        "mate": [],
        "previous_mates": [],
        "dead": true,
        "paralyzed": false,
        "no_kits": false,
        "exiled": false,
        "pelt_name": "Speckled",
        "pelt_color": "PALEGREY",
        "pelt_length": "short",
        "sprite_kitten": 0,
        "sprite_adolescent": 5,
        "sprite_adult": 8,
        "sprite_senior": 12,
        "sprite_para_adult": 15,
        "eye_colour": "PALEYELLOW",
        "eye_colour2": null,
        "reverse": true,
        "white_patches": null,
        "vitiligo": null,
        "points": null,
        "white_patches_tint": "none",
        "pattern": null,
        "tortie_base": null,
        "tortie_color": null,
        "tortie_pattern": null,
        "skin": "BLACK",
        "tint": "black",
        "skill_dict": {
            "primary": "RUNNER,12,False",
            "secondary": "MEDIATOR,0,False",
            "hidden": null
        },
        "scars": [],
        "accessory": null,
        "experience": 297,
        "dead_moons": 15,
        "current_apprentice": [],
        "former_apprentices": [],
        "df": false,
        "outside": false,
        "otherclan1": true,
        "clan": "Speckle",
        "faded_offspring": [],
        "opacity": 99,
        "prevent_fading": false,
        "favourite": false
    },
    {
        "ID": "58",
        "name_prefix": "Ice",
        "name_suffix": "clove",
        "specsuffix_hidden": false,
        "gender": "male",
        "gender_align": "male",
        "birth_cooldown": 0,
        "status": "mediator",
        "backstory": "clanborn",
        "moons": 72,
        "trait": "charismatic",
        "facets": "8,11,9,3",
        "parent1": null,
        "parent2": null,
        "adoptive_parents": [],
        "mentor": null,
        "former_mentor": [],
        "patrol_with_mentor": 0,
        "mate": [],
        "previous_mates": [],
        "dead": false,
        "paralyzed": false,
        "no_kits": false,
        "exiled": false,
        "pelt_name": "Singlestripe",
        "pelt_color": "SILVER",
        "pelt_length": "long",
        "sprite_kitten": 0,
        "sprite_adolescent": 5,
        "sprite_adult": 10,
        "sprite_senior": 14,
        "sprite_para_adult": 15,
        "eye_colour": "YELLOW",
        "eye_colour2": null,
        "reverse": true,
        "white_patches": null,
        "vitiligo": null,
        "points": null,
        "white_patches_tint": "none",
        "pattern": null,
        "tortie_base": null,
        "tortie_color": null,
        "tortie_pattern": null,
        "skin": "PEACH",
        "tint": "black",
        "skill_dict": {
            "primary": "STORY,17,False",
            "secondary": "LORE,13,False",
            "hidden": null
        },
        "scars": [],
        "accessory": null,
        "experience": 110,
        "dead_moons": 0,
        "current_apprentice": [],
        "former_apprentices": [],
        "df": false,
        "outside": true,
        "otherclan1": true,
        "clan": "Speckle",
        "faded_offspring": [],
        "opacity": 100,
        "prevent_fading": false,
        "favourite": false
    },
    {
        "ID": "59",
        "name_prefix": "Whimsy",
        "name_suffix": "buzz",
        "specsuffix_hidden": false,
        "gender": "male",
        "gender_align": "male",
        "birth_cooldown": 0,
        "status": "leader",
        "backstory": "clanborn",
        "moons": 59,
        "trait": "adventurous",
        "facets": "3,12,9,13",
        "parent1": null,
        "parent2": null,
        "adoptive_parents": [],
        "mentor": null,
        "former_mentor": [],
        "patrol_with_mentor": 0,
        "mate": [],
        "previous_mates": [],
        "dead": false,
        "paralyzed": false,
        "no_kits": false,
        "exiled": false,
        "pelt_name": "SingleColour",
        "pelt_color": "LIGHTBROWN",
        "pelt_length": "short",
        "sprite_kitten": 1,
        "sprite_adolescent": 4,
        "sprite_adult": 7,
        "sprite_senior": 14,
        "sprite_para_adult": 15,
        "eye_colour": "PALEYELLOW",
        "eye_colour2": null,
        "reverse": true,
        "white_patches": "COWTWO",
        "vitiligo": null,
        "points": null,
        "white_patches_tint": "offwhite",
        "pattern": null,
        "tortie_base": null,
        "tortie_color": null,
        "tortie_pattern": null,
        "skin": "LIGHTBROWN",
        "tint": "purple",
        "skill_dict": {
            "primary": "MEDIATOR,13,False",
            "secondary": null,
            "hidden": null
        },
        "scars": [],
        "accessory": null,
        "experience": 194,
        "dead_moons": 0,
        "current_apprentice": [],
        "former_apprentices": [
            "50",
            "51"
        ],
        "df": false,
        "outside": true,
        "otherclan1": true,
        "clan": "Speckle",
        "faded_offspring": [],
        "opacity": 100,
        "prevent_fading": false,
        "favourite": false
    },
    {
        "ID": "60",
        "name_prefix": "Lupine",
        "name_suffix": "ash",
        "specsuffix_hidden": false,
        "gender": "male",
        "gender_align": "male",
        "birth_cooldown": 0,
        "status": "deputy",
        "backstory": "clanborn",
        "moons": 67,
        "trait": "ambitious",
        "facets": "11,13,9,4",
        "parent1": null,
        "parent2": null,
        "adoptive_parents": [],
        "mentor": null,
        "former_mentor": [],
        "patrol_with_mentor": 0,
        "mate": [],
        "previous_mates": [],
        "dead": true,
        "paralyzed": false,
        "no_kits": false,
        "exiled": false,
        "pelt_name": "Bengal",
        "pelt_color": "DARKGREY",
        "pelt_length": "medium",
        "sprite_kitten": 2,
        "sprite_adolescent": 4,
        "sprite_adult": 7,
        "sprite_senior": 12,
        "sprite_para_adult": 15,
        "eye_colour": "PALEBLUE",
        "eye_colour2": null,
        "reverse": false,
        "white_patches": "REVERSEHEART",
        "vitiligo": null,
        "points": null,
        "white_patches_tint": "darkcream",
        "pattern": null,
        "tortie_base": null,
        "tortie_color": null,
        "tortie_pattern": null,
        "skin": "DARKBROWN",
        "tint": "none",
        "skill_dict": {
            "primary": "SWIMMER,28,False",
            "secondary": "LORE,6,False",
            "hidden": null
        },
        "scars": [],
        "accessory": null,
        "experience": 138,
        "dead_moons": 12,
        "current_apprentice": [],
        "former_apprentices": [
            "50"
        ],
        "df": false,
        "outside": false,
        "otherclan1": true,
        "clan": "Speckle",
        "faded_offspring": [],
        "opacity": 99,
        "prevent_fading": false,
        "favourite": false
    },
    {
        "ID": "1",
        "name_prefix": "Pheasant",
        "name_suffix": "puddle",
        "specsuffix_hidden": false,
        "gender": "female",
        "gender_align": "female",
        "birth_cooldown": 0,
        "status": "warrior",
        "backstory": "clanborn",
        "moons": 69,
        "trait": "troublesome",
        "facets": "2,0,6,0",
        "parent1": null,
        "parent2": null,
        "adoptive_parents": [],
        "mentor": null,
        "former_mentor": [],
        "patrol_with_mentor": 0,
        "mate": [],
        "previous_mates": [],
        "dead": false,
        "paralyzed": false,
        "no_kits": false,
        "exiled": false,
        "pelt_name": "SingleColour",
        "pelt_color": "SILVER",
        "pelt_length": "long",
        "sprite_kitten": 0,
        "sprite_adolescent": 5,
        "sprite_adult": 9,
        "sprite_senior": 14,
        "sprite_para_adult": 15,
        "eye_colour": "SUNLITICE",
        "eye_colour2": null,
        "reverse": false,
        "white_patches": "ONEEAR",
        "vitiligo": null,
        "points": null,
        "white_patches_tint": "none",
        "pattern": null,
        "tortie_base": null,
        "tortie_color": null,
        "tortie_pattern": null,
        "skin": "DARKGREY",
        "tint": "gray",
        "skill_dict": {
            "primary": "CLIMBER,26,False",
            "secondary": null,
            "hidden": null
        },
        "scars": [
            "BRIDGE"
        ],
        "accessory": null,
        "experience": 102,
        "dead_moons": 0,
        "current_apprentice": [],
        "former_apprentices": [],
        "df": false,
        "outside": true,
        "otherclan1": true,
        "clan": "Speckle",
        "faded_offspring": [],
        "opacity": 100,
        "prevent_fading": false,
        "favourite": false
    }
]